
[
  {
    "title": "CineDev",
    "imageSrc": "projeto1.png",
    "description": "This is a project about cinema,ticket shop. Multi pages",
    "skills": ["Next", "Typescript", "css"],
    "demo": "https://cine-phi.vercel.app/",
    "source": "https://github.com/DocCaio/CineDev"
  },
  {
    "title": "Wild-Life-Zoo",
    "imageSrc": "projeto2.png",
    "description": "This is a project about a zoo and buy ticket shop. Multi pages ",
    "skills": ["React", "Vite", "Swiper", "Boostrap"],
    "demo": "https://wild-life-pink.vercel.app/",
    "source": "https://github.com/DocCaio/Wild-Life"
  },
  {
    "title": "Project C",
    "imageSrc": "project.png",
    "description": "This is a project made to learn the latest languages by building an app.",
    "skills": ["React", "Express", "Node"],
    "demo": "https://www.example.com",
    "source": "https://www.github.com"
  },
  {
    "title": "Project D",
    "imageSrc": "project.png",
    "description": "This is a project made to learn the latest languages by building an app.",
    "skills": ["React", "Express", "Node"],
    "demo": "https://www.example.com",
    "source": "https://www.github.com"
  },

  {
    "title": "Project E",
    "imageSrc": "project.png",
    "description": "This is a project made to learn the latest languages by building an app.",
    "skills": ["React", "Express", "Node"],
    "demo": "https://www.example.com",
    "source": "https://www.github.com"
  },

{
  "title": "Project F",
  "imageSrc": "project.png",
  "description": "This is a project made to learn the latest languages by building an app.",
  "skills": ["React", "Express", "Node"],
  "demo": "https://www.example.com",
  "source": "https://www.github.com"
}

]
